secure_query/__init__.py
secure_query/crypto.py
secure_query/router.py
secure_query/settings.py
secure_query-0.1.4.dist-info/licenses/LICENSE
secure_query-0.1.4.dist-info/METADATA
secure_query-0.1.4.dist-info/WHEEL
secure_query-0.1.4.dist-info/top_level.txt
secure_query-0.1.4.dist-info/RECORD
