Metadata-Version: 2.4
Name: secure-query
Version: 0.1.4
Summary: Encrypt query payloads in frontend and decrypt in FastAPI using RSA-OAEP encryption with built-in security features.
Author-email: Secure Query Contributors <contributors@secure-query.dev>
Maintainer-email: Secure Query Contributors <contributors@secure-query.dev>
License: MIT
Project-URL: Homepage, https://github.com/Kshitiz-Srivastava0/secure-query
Project-URL: Documentation, https://github.com/Kshitiz-Srivastava0/secure-query#readme
Project-URL: Repository, https://github.com/Kshitiz-Srivastava0/secure-query.git
Project-URL: Bug Tracker, https://github.com/Kshitiz-Srivastava0/secure-query/issues
Project-URL: Changelog, https://github.com/Kshitiz-Srivastava0/secure-query/blob/main/CHANGELOG.md
Keywords: encryption,security,fastapi,rsa,oaep,crypto,privacy,query,payload,frontend,backend,web,api
Classifier: Development Status :: 4 - Beta
Classifier: Intended Audience :: Developers
Classifier: License :: OSI Approved :: MIT License
Classifier: Operating System :: OS Independent
Classifier: Programming Language :: Python :: 3
Classifier: Programming Language :: Python :: 3.9
Classifier: Programming Language :: Python :: 3.10
Classifier: Programming Language :: Python :: 3.11
Classifier: Programming Language :: Python :: 3.12
Classifier: Framework :: FastAPI
Classifier: Topic :: Security :: Cryptography
Classifier: Topic :: Software Development :: Libraries :: Python Modules
Classifier: Topic :: Internet :: WWW/HTTP :: HTTP Servers
Classifier: Typing :: Typed
Requires-Python: >=3.9
License-File: LICENSE
Requires-Dist: cryptography<45,>=42
Provides-Extra: fastapi
Requires-Dist: fastapi<1.0,>=0.110; extra == "fastapi"
Provides-Extra: test
Requires-Dist: pytest>=7.0; extra == "test"
Requires-Dist: pytest-cov>=4.0; extra == "test"
Requires-Dist: fastapi<1.0,>=0.110; extra == "test"
Requires-Dist: httpx>=0.24.0; extra == "test"
Dynamic: license-file
